{
	"name": "DestinationDataset_pxn",
	"properties": {
		"linkedServiceName": {
			"referenceName": "dwhdatalakedevelopment",
			"type": "LinkedServiceReference"
		},
		"parameters": {
			"cw_fileName": {
				"type": "String"
			}
		},
		"annotations": [],
		"type": "Parquet",
		"typeProperties": {
			"location": {
				"type": "AzureBlobFSLocation",
				"fileName": {
					"value": "@dataset().cw_fileName",
					"type": "Expression"
				},
				"folderPath": "Other",
				"fileSystem": "dwh-stage"
			},
			"compressionCodec": "snappy"
		},
		"schema": []
	}
}